[
        {
            "question": "What is the capital of France?",
            "option": {
                "paris" : true,
                "london" : false,
                "berlin" : false,
                "madrid" : false
            }
        }
        ,{
            "question": "what is the biggest planet in our solar system?",
            "option": {   
            "earth": false,
            "mars": false,
            "jupiter": true,
            "saturn": false} 
        }
        ,{
            "question": "What is the largest mammal in the world?",
            "option": {
            "elephant": false,
            "blue whale": true,
            "giraffe": false,
            "hippopotamus": false}
        },
        {
            "question": "What is the largest ocean in the world?",
            "option":{
            "atlantic": false,
            "indian": false,
            "pacific": true,
            "arctic": false}
        }
]
